README.rst
setup.py
entity_uploader/__init__.py
nyt_entity_uploader.egg-info/PKG-INFO
nyt_entity_uploader.egg-info/SOURCES.txt
nyt_entity_uploader.egg-info/dependency_links.txt
nyt_entity_uploader.egg-info/requires.txt
nyt_entity_uploader.egg-info/top_level.txt