Metadata-Version: 1.1
Name: nyt-entity-uploader
Version: 0.0.1
Summary: Wrapper for making POST requests to an NYT entity service API.
Home-page: https://github.com/newsdev/nyt-pyiap
Author: Jeremy Bowers
Author-email: jeremy.bowers@nytimes.com
License: Apache License 2.0
Keywords: entity entity-service nyt
Platform: UNKNOWN
Classifier: Development Status :: 3 - Alpha
Classifier: Intended Audience :: Developers
Classifier: Topic :: Software Development :: Libraries :: Python Modules
Classifier: Programming Language :: Python
Classifier: Programming Language :: Python :: 3
Classifier: Programming Language :: Python :: 3.6
